pelican/plugins/tag_cloud/__init__.py
pelican/plugins/tag_cloud/tag_cloud.py
pelican/plugins/tag_cloud/test_data/article_1.md
pelican/plugins/tag_cloud/test_data/article_2.md
pelican/plugins/tag_cloud/test_data/article_3.md
pelican/plugins/tag_cloud/test_data/article_4.md
pelican/plugins/tag_cloud/test_data/article_5.md
pelican/plugins/tag_cloud/test_tag_cloud.py
pelican_tag_cloud-1.0.0.dist-info/WHEEL
pelican_tag_cloud-1.0.0.dist-info/METADATA
pelican_tag_cloud-1.0.0.dist-info/RECORD
